ovos_audio_gender_classifier/__init__.py
ovos_audio_gender_classifier/version.py
ovos_audio_classifier_gender-0.0.0a2.dist-info/METADATA
ovos_audio_classifier_gender-0.0.0a2.dist-info/WHEEL
ovos_audio_classifier_gender-0.0.0a2.dist-info/entry_points.txt
ovos_audio_classifier_gender-0.0.0a2.dist-info/top_level.txt
ovos_audio_classifier_gender-0.0.0a2.dist-info/zip-safe
ovos_audio_classifier_gender-0.0.0a2.dist-info/RECORD
